[
  {
    "number": 2,
    "title": "Боже крепки и всесилни",
    "alias": "",
    "ppt": "https://cloud.adventist.bg/index.php/s/eqF6nCiZG54gZrM/download",
    "text": "https://cloud.adventist.bg/index.php/s/7w57HsKQ4Abk4dW/download",
    "notes": "https://cloud.adventist.bg/index.php/s/FXZgGwgTfEwwZZn/download",
    "music": ""
  },
  {
    "number": 4,
    "title": "Боже, отвори вратата",
    "alias": "",
    "ppt": "https://cloud.adventist.bg/index.php/s/WGQ7mktL9aGFWyG/download",
    "text": "https://cloud.adventist.bg/index.php/s/9oWw4r4cffJLWDA/download",
    "notes": "https://cloud.adventist.bg/index.php/s/pPDiTRCf4447iY6/download",
    "music": ""
  },
  {
    "number": 5,
    "title": "Както еленът за вода студена",
    "alias": "",
    "ppt": "https://cloud.adventist.bg/index.php/s/NaA9LJoLAXL25cg/download",
    "text": "https://cloud.adventist.bg/index.php/s/BM9f967NTbB8Jjm/download",
    "notes": "https://cloud.adventist.bg/index.php/s/HMbN394HmRfQM9T/download",
    "music": ""
  },
  {
    "number": 6,
    "title": "Господи, ние пак сме гладни",
    "alias": "",
    "ppt": "https://cloud.adventist.bg/index.php/s/4SWnna45ymCLa5g/download",
    "text": "https://cloud.adventist.bg/index.php/s/eRfkk7g8moLLDRa/download",
    "notes": "https://cloud.adventist.bg/index.php/s/BJybrKPJggNMs43/download",
    "music": ""
  },
  {
    "number": 7,
    "title": "Слава на Бога",
    "alias": "Хвалете Бога",
    "ppt": "https://cloud.adventist.bg/index.php/s/TcS7GCijx77aJ2Y/download",
    "text": "https://cloud.adventist.bg/index.php/s/TfQBEyQcBZHmGKs/download",
    "notes": "https://cloud.adventist.bg/index.php/s/JNwcfiwZwZE6t79/download",
    "music": ""
  },
  {
    "number": 8,
    "title": "Слава на Господа",
    "alias": "",
    "ppt": "https://cloud.adventist.bg/index.php/s/RTordp2NPZPMXrA/download",
    "text": "https://cloud.adventist.bg/index.php/s/nfcJ8XwEMiNXBoE/download",
    "notes": "https://cloud.adventist.bg/index.php/s/3HKWtEmZynSXcaZ/download",
    "music": ""
  },
  {
    "number": 9,
    "title": "Разказва ни небесна шир",
    "alias": "",
    "ppt": "https://cloud.adventist.bg/index.php/s/G9A9jmqPDSsQXL5/download",
    "text": "https://cloud.adventist.bg/index.php/s/2taEpwQWHAH3wEm/download",
    "notes": "https://cloud.adventist.bg/index.php/s/Fj3LCq5o78BRWdz/download",
    "music": ""
  },
  {
    "number": 10,
    "title": "Свят, свят, свят си, Боже",
    "alias": "",
    "ppt": "https://cloud.adventist.bg/index.php/s/b8Yk9eQzSMEJArG/download",
    "text": "https://cloud.adventist.bg/index.php/s/63TPd2tYQcsoekM/download",
    "notes": "https://cloud.adventist.bg/index.php/s/2LjANzKLyFrEDMX/download",
    "music": ""
  },
  {
    "number": 12,
    "title": "О, велики Боже наш",
    "alias": "",
    "ppt": "https://cloud.adventist.bg/index.php/s/LBRaRT6QFtbCyew/download",
    "text": "https://cloud.adventist.bg/index.php/s/nbJZ69MNK6NFFGP/download",
    "notes": "https://cloud.adventist.bg/index.php/s/bi5LL3xpQkM3KfE/download",
    "music": ""
  },
  {
    "number": 13,
    "title": "О, Боже, велик е за нас Твоят дар",
    "alias": "О, Боже, безцен",
    "ppt": "LINK/download",
    "text": "LINK/download",
    "notes": "LINK/download",
    "music": ""
  },
  {
    "number": 14,
    "title": "Исусе, обичам Те",
    "alias": "Исусе, Теб любя",
    "ppt": "LINK/download",
    "text": "LINK/download",
    "notes": "LINK/download",
    "music": ""
  },
  {
    "number": 17,
    "title": "Святи Дух, наш Утешител",
    "alias": "О, всевечни Душе Святи",
    "ppt": "LINK/download",
    "text": "LINK/download",
    "notes": "LINK/download",
    "music": ""
  },
  {
    "number": 18,
    "title": "О, животворен Дух Свети",
    "alias": "",
    "ppt": "LINK/download",
    "text": "LINK/download",
    "notes": "LINK/download",
    "music": ""
  },
  {
    "number": 19,
    "title": "Чуйте днес глас евангелски",
    "alias": "Чуйте тоз глас евангелски",
    "ppt": "LINK/download",
    "text": "LINK/download",
    "notes": "LINK/download",
    "music": ""
  },
  {
    "number": 20,
    "title": "Живот и светлина е Словото",
    "alias": "Твоето Слово нам",
    "ppt": "LINK/download",
    "text": "LINK/download",
    "notes": "LINK/download",
    "music": ""
  },
  {
    "number": 21,
    "title": "Чуйте всички тази вест",
    "alias": "Вий от близо и далеч",
    "ppt": "LINK/download",
    "text": "LINK/download",
    "notes": "LINK/download",
    "music": ""
  },
  {
    "number": 24,
    "title": "О, чудна стара повест",
    "alias": "Чудната стара повест",
    "ppt": "LINK/download",
    "text": "LINK/download",
    "notes": "LINK/download",
    "music": ""
  },
  {
    "number": 25,
    "title": "Святата Библия",
    "alias": "",
    "ppt": "LINK/download",
    "text": "LINK/download",
    "notes": "LINK/download",
    "music": ""
  },
  {
    "number": 26,
    "title": "О, чудно е Божието Слово",
    "alias": "",
    "ppt": "LINK/download",
    "text": "LINK/download",
    "notes": "LINK/download",
    "music": ""
  },
  {
    "number": 27,
    "title": "Обичам да разказвам",
    "alias": "Обичам да приказвам",
    "ppt": "LINK/download",
    "text": "LINK/download",
    "notes": "LINK/download",
    "music": ""
  },
  {
    "number": 28,
    "title": "Пак безопасно преведе ни Той",
    "alias": "Пак безопасно преминахме ний",
    "ppt": "LINK/download",
    "text": "LINK/download",
    "notes": "LINK/download",
    "music": ""
  },
  {
    "number": 29,
    "title": "О, ден на радост свята",
    "alias": "",
    "ppt": "LINK/download",
    "text": "LINK/download",
    "notes": "LINK/download",
    "music": ""
  },
  {
    "number": 30,
    "title": "Ето, настъпи съботният ден",
    "alias": "Дошъл е пак денят на свят покой",
    "ppt": "LINK/download",
    "text": "LINK/download",
    "notes": "LINK/download",
    "music": ""
  },
  {
    "number": 31,
    "title": "Светла е зората",
    "alias": "",
    "ppt": "LINK/download",
    "text": "LINK/download",
    "notes": "LINK/download",
    "music": ""
  },
  {
    "number": 32,
    "title": "Едно чудесно място знам",
    "alias": "",
    "ppt": "LINK/download",
    "text": "LINK/download",
    "notes": "LINK/download",
    "music": ""
  },
  {
    "number": 33,
    "title": "О, Учителю небесни",
    "alias": "",
    "ppt": "LINK/download",
    "text": "LINK/download",
    "notes": "LINK/download",
    "music": ""
  },
  {
    "number": 34,
    "title": "Радостно ликуват нашите сърца",
    "alias": "Радостни са днеска нашите сърца",
    "ppt": "LINK/download",
    "text": "LINK/download",
    "notes": "LINK/download",
    "music": ""
  },
  {
    "number": 36,
    "title": "Алилуя! Светло утро",
    "alias": "",
    "ppt": "LINK/download",
    "text": "LINK/download",
    "notes": "LINK/download",
    "music": ""
  },
  {
    "number": 37,
    "title": "О, събота свята",
    "alias": "Събота блажена",
    "ppt": "LINK/download",
    "text": "LINK/download",
    "notes": "LINK/download",
    "music": ""
  },
  {
    "number": 39,
    "title": "Господната събота свята",
    "alias": "",
    "ppt": "LINK/download",
    "text": "LINK/download",
    "notes": "LINK/download",
    "music": ""
  },
  {
    "number": 40,
    "title": "О, съботно училище",
    "alias": "",
    "ppt": "LINK/download",
    "text": "LINK/download",
    "notes": "LINK/download",
    "music": ""
  },
  {
    "number": 43,
    "title": "Мил Отче наш във небеса",
    "alias": "",
    "ppt": "LINK/download",
    "text": "LINK/download",
    "notes": "LINK/download",
    "music": ""
  },
  {
    "number": 45,
    "title": "Мир, радост и прощение",
    "alias": "Таз радост, мир, прощение",
    "ppt": "LINK/download",
    "text": "LINK/download",
    "notes": "LINK/download",
    "music": ""
  },
  {
    "number": 48,
    "title": "Исус – чудно, свято име!",
    "alias": "Исус - туй чудесно име",
    "ppt": "LINK/download",
    "text": "LINK/download",
    "notes": "LINK/download",
    "music": ""
  },
  {
    "number": 49,
    "title": "Исус, моя радост",
    "alias": "",
    "ppt": "LINK/download",
    "text": "LINK/download",
    "notes": "LINK/download",
    "music": ""
  },
  {
    "number": 51,
    "title": "Аз ще възпея Теб, Исусе",
    "alias": "Аз ще възпея на Исуса",
    "ppt": "LINK/download",
    "text": "LINK/download",
    "notes": "LINK/download",
    "music": ""
  },
  {
    "number": 53,
    "title": "Исусе драгоценни",
    "alias": "",
    "ppt": "LINK/download",
    "text": "LINK/download",
    "notes": "LINK/download",
    "music": ""
  },
  {
    "number": 61,
    "title": "Чух сладия Исусов глас",
    "alias": "",
    "ppt": "LINK/download",
    "text": "LINK/download",
    "notes": "LINK/download",
    "music": ""
  },
  {
    "number": 73,
    "title": "Живота Си съм дал за теб",
    "alias": "Живота Си за теб",
    "ppt": "LINK/download",
    "text": "LINK/download",
    "notes": "LINK/download",
    "music": ""
  },
  {
    "number": 76,
    "title": "Аз зная, жив е Господ мой",
    "alias": "",
    "ppt": "LINK/download",
    "text": "LINK/download",
    "notes": "LINK/download",
    "music": ""
  },
  {
    "number": 77,
    "title": "Не знаем кога Бог ще дойде",
    "alias": "Не знаем кога Той ще дойде",
    "ppt": "LINK/download",
    "text": "LINK/download",
    "notes": "LINK/download",
    "music": ""
  },
  {
    "number": 87,
    "title": "Спасен! Спасен!",
    "alias": "",
    "ppt": "LINK/download",
    "text": "LINK/download",
    "notes": "LINK/download",
    "music": ""
  },
  {
    "number": 92,
    "title": "Живот има във поглед към Христа",
    "alias": "",
    "ppt": "LINK/download",
    "text": "LINK/download",
    "notes": "LINK/download",
    "music": ""
  },
  {
    "number": 97,
    "title": "Такъв, какъвто съм",
    "alias": "",
    "ppt": "LINK/download",
    "text": "LINK/download",
    "notes": "LINK/download",
    "music": ""
  },
  {
    "number": 102,
    "title": "Мир сладък",
    "alias": "",
    "ppt": "LINK/download",
    "text": "LINK/download",
    "notes": "LINK/download",
    "music": ""
  },
  {
    "number": 103,
    "title": "От какво ли се нуждая",
    "alias": "От що друго се нуждая",
    "ppt": "LINK/download",
    "text": "LINK/download",
    "notes": "LINK/download",
    "music": ""
  },
  {
    "number": 130,
    "title": "Вдъхнал си ми, Боже, вяра",
    "alias": "",
    "ppt": "LINK/download",
    "text": "LINK/download",
    "notes": "LINK/download",
    "music": ""
  },
  {
    "number": 137,
    "title": "Честит за мен е този ден",
    "alias": "Честит тоз ден",
    "ppt": "LINK/download",
    "text": "LINK/download",
    "notes": "LINK/download",
    "music": ""
  },
  {
    "number": 138,
    "title": "Радост нечута затрепва у мен",
    "alias": "",
    "ppt": "LINK/download",
    "text": "LINK/download",
    "notes": "LINK/download",
    "music": ""
  },
  {
    "number": 140,
    "title": "Бог е силен мой помощник",
    "alias": "",
    "ppt": "LINK/download",
    "text": "LINK/download",
    "notes": "LINK/download",
    "music": ""
  },
  {
    "number": 141,
    "title": "Слънце ярко",
    "alias": "",
    "ppt": "LINK/download",
    "text": "LINK/download",
    "notes": "LINK/download",
    "music": ""
  },
  {
    "number": 146,
    "title": "Вярвай просто всеки ден",
    "alias": "",
    "ppt": "LINK/download",
    "text": "LINK/download",
    "notes": "LINK/download",
    "music": ""
  },
  {
    "number": 149,
    "title": "Уповавам в Теб, Исусе",
    "alias": "",
    "ppt": "LINK/download",
    "text": "LINK/download",
    "notes": "LINK/download",
    "music": ""
  },
  {
    "number": 150,
    "title": "О, Любов пречудна, свята",
    "alias": "",
    "ppt": "LINK/download",
    "text": "LINK/download",
    "notes": "LINK/download",
    "music": ""
  },
  {
    "number": 156,
    "title": "Бог по претайни начини",
    "alias": "",
    "ppt": "LINK/download",
    "text": "LINK/download",
    "notes": "LINK/download",
    "music": ""
  },
  {
    "number": 167,
    "title": "Имам Приятел мил",
    "alias": "Приятел небесен",
    "ppt": "LINK/download",
    "text": "LINK/download",
    "notes": "LINK/download",
    "music": ""
  },
  {
    "number": 172,
    "title": "Както баща милее за син",
    "alias": "",
    "ppt": "LINK/download",
    "text": "LINK/download",
    "notes": "LINK/download",
    "music": ""
  },
  {
    "number": 176,
    "title": "О, не отминавай, Боже",
    "alias": "",
    "ppt": "LINK/download",
    "text": "LINK/download",
    "notes": "LINK/download",
    "music": ""
  },
  {
    "number": 177,
    "title": "Колко скъп и мил Приятел",
    "alias": "Колко скъп е тоз Приятел",
    "ppt": "LINK/download",
    "text": "LINK/download",
    "notes": "LINK/download",
    "music": ""
  },
  {
    "number": 182,
    "title": "При Теб, о, Боже мой",
    "alias": "",
    "ppt": "LINK/download",
    "text": "LINK/download",
    "notes": "LINK/download",
    "music": ""
  },
  {
    "number": 192,
    "title": "Мойте стъпки отправи",
    "alias": "",
    "ppt": "LINK/download",
    "text": "LINK/download",
    "notes": "LINK/download",
    "music": ""
  },
  {
    "number": 196,
    "title": "О,колко радост в мисълта",
    "alias": "",
    "ppt": "LINK/download",
    "text": "LINK/download",
    "notes": "LINK/download",
    "music": ""
  },
  {
    "number": 200,
    "title": "Мили Пастирю, води ни",
    "alias": "Спасе, като овчар води ни",
    "ppt": "LINK/download",
    "text": "LINK/download",
    "notes": "LINK/download",
    "music": ""
  },
  {
    "number": 203,
    "title": "О, безопасно място",
    "alias": "",
    "ppt": "LINK/download",
    "text": "LINK/download",
    "notes": "LINK/download",
    "music": ""
  },
  {
    "number": 206,
    "title": "Сред бурите в живота ни",
    "alias": "Сред бурите на тоз живот",
    "ppt": "LINK/download",
    "text": "LINK/download",
    "notes": "LINK/download",
    "music": ""
  },
  {
    "number": 223,
    "title": "Почтено чувство е да негодуваш",
    "alias": "",
    "ppt": "LINK/download",
    "text": "LINK/download",
    "notes": "LINK/download",
    "music": ""
  },
  {
    "number": 226,
    "title": "Със сърца съединени",
    "alias": "",
    "ppt": "LINK/download",
    "text": "LINK/download",
    "notes": "LINK/download",
    "music": ""
  },
  {
    "number": 233,
    "title": "Сейте, сеячи",
    "alias": "",
    "ppt": "LINK/download",
    "text": "LINK/download",
    "notes": "LINK/download",
    "music": ""
  },
  {
    "number": 236,
    "title": "Снопи носят те",
    "alias": "Тези, що със сълзи добро семе сеят",
    "ppt": "LINK/download",
    "text": "LINK/download",
    "notes": "LINK/download",
    "music": ""
  },
  {
    "number": 251,
    "title": "Господ те кани",
    "alias": "Ела при Спаса",
    "ppt": "LINK/download",
    "text": "LINK/download",
    "notes": "LINK/download",
    "music": ""
  },
  {
    "number": 279,
    "title": "Бог ме обича",
    "alias": "Бог е любовта",
    "ppt": "LINK/download",
    "text": "LINK/download",
    "notes": "LINK/download",
    "music": ""
  },
  {
    "number": 281,
    "title": "Весели да са сърцата",
    "alias": "",
    "ppt": "LINK/download",
    "text": "LINK/download",
    "notes": "LINK/download",
    "music": ""
  },
  {
    "number": 500,
    "title": "Блика надежда",
    "alias": "",
    "ppt": "LINK/download",
    "text": "LINK/download",
    "notes": "LINK/download",
    "music": ""
  },
  {
    "number": 501,
    "title": "Аз съм твой Бог",
    "alias": "",
    "ppt": "LINK/download",
    "text": "LINK/download",
    "notes": "LINK/download",
    "music": ""
  },
  {
    "number": 502,
    "title": "Величие",
    "alias": "",
    "ppt": "LINK/download",
    "text": "LINK/download",
    "notes": "LINK/download",
    "music": ""
  },
  {
    "number": 503,
    "title": "Господ Исус е наша надежда",
    "alias": "",
    "ppt": "LINK/download",
    "text": "LINK/download",
    "notes": "LINK/download",
    "music": ""
  },
  {
    "number": 504,
    "title": "Денят изгряващ да бъде по-красив",
    "alias": "",
    "ppt": "LINK/download",
    "text": "LINK/download",
    "notes": "LINK/download",
    "music": ""
  },
  {
    "number": 505,
    "title": "Ето ме",
    "alias": "",
    "ppt": "LINK/download",
    "text": "LINK/download",
    "notes": "LINK/download",
    "music": ""
  },
  {
    "number": 506,
    "title": "Живи потоци",
    "alias": "",
    "ppt": "LINK/download",
    "text": "LINK/download",
    "notes": "LINK/download",
    "music": ""
  },
  {
    "number": 507,
    "title": "Зная, навеки мой е Исус",
    "alias": "Ти християнин ли си",
    "ppt": "LINK/download",
    "text": "LINK/download",
    "notes": "LINK/download",
    "music": ""
  },
  {
    "number": 508,
    "title": "Изкупен",
    "alias": "",
    "ppt": "LINK/download",
    "text": "LINK/download",
    "notes": "LINK/download",
    "music": ""
  },
  {
    "number": 509,
    "title": "Колко радостен ще бъда",
    "alias": "",
    "ppt": "LINK/download",
    "text": "LINK/download",
    "notes": "LINK/download",
    "music": ""
  },
  {
    "number": 510,
    "title": "На Бог вечна слава",
    "alias": "",
    "ppt": "LINK/download",
    "text": "LINK/download",
    "notes": "LINK/download",
    "music": ""
  },
  {
    "number": 511,
    "title": "Надежда моя е Христос",
    "alias": "",
    "ppt": "LINK/download",
    "text": "LINK/download",
    "notes": "LINK/download",
    "music": ""
  },
  {
    "number": 512,
    "title": "Нека Бог да те благослови",
    "alias": "",
    "ppt": "LINK/download",
    "text": "LINK/download",
    "notes": "LINK/download",
    "music": ""
  },
  {
    "number": 513,
    "title": "О, чудна милост",
    "alias": "",
    "ppt": "LINK/download",
    "text": "LINK/download",
    "notes": "LINK/download",
    "music": ""
  },
  {
    "number": 514,
    "title": "Всичко на Исус предавам",
    "alias": "",
    "ppt": "LINK/download",
    "text": "LINK/download",
    "notes": "LINK/download",
    "music": ""
  },
  {
    "number": 515,
    "title": "Мой Пастир е Господ Исус Христос",
    "alias": "",
    "ppt": "LINK/download",
    "text": "LINK/download",
    "notes": "LINK/download",
    "music": ""
  },
  {
    "number": 516,
    "title": "Свят си, Боже",
    "alias": "",
    "ppt": "LINK/download",
    "text": "LINK/download",
    "notes": "LINK/download",
    "music": ""
  },
  {
    "number": 517,
    "title": "Със Исуса вървим",
    "alias": "",
    "ppt": "LINK/download",
    "text": "LINK/download",
    "notes": "LINK/download",
    "music": ""
  },
  {
    "number": 518,
    "title": "Верен си, Господи",
    "alias": "",
    "ppt": "LINK/download",
    "text": "LINK/download",
    "notes": "LINK/download",
    "music": ""
  },
  {
    "number": 519,
    "title": "Измий сърцето ми",
    "alias": "",
    "ppt": "LINK/download",
    "text": "LINK/download",
    "notes": "LINK/download",
    "music": ""
  },
  {
    "number": 520,
    "title": "Исус е жив",
    "alias": "",
    "ppt": "LINK/download",
    "text": "LINK/download",
    "notes": "LINK/download",
    "music": ""
  },
  {
    "number": 521,
    "title": "Славен дом, вечен дом",
    "alias": "",
    "ppt": "LINK/download",
    "text": "LINK/download",
    "notes": "LINK/download",
    "music": ""
  },
  {
    "number": 522,
    "title": "Близо, по-близо",
    "alias": "",
    "ppt": "LINK/download",
    "text": "LINK/download",
    "notes": "LINK/download",
    "music": ""
  },
  {
    "number": 523,
    "title": "Ти, Който свят си, Господи",
    "alias": "",
    "ppt": "LINK/download",
    "text": "LINK/download",
    "notes": "LINK/download",
    "music": ""
  },
  {
    "number": 524,
    "title": "Всичко за мен си Ти",
    "alias": "",
    "ppt": "LINK/download",
    "text": "LINK/download",
    "notes": "LINK/download",
    "music": ""
  },
  {
    "number": 525,
    "title": "Бог знае, Бог чува, Бог вижда",
    "alias": "",
    "ppt": "LINK/download",
    "text": "LINK/download",
    "notes": "LINK/download",
    "music": ""
  },
  {
    "number": 526,
    "title": "Сей вестта",
    "alias": "",
    "ppt": "LINK/download",
    "text": "LINK/download",
    "notes": "LINK/download",
    "music": ""
  },
  {
    "number": 527,
    "title": "Слава на Бог",
    "alias": "",
    "ppt": "LINK/download",
    "text": "LINK/download",
    "notes": "LINK/download",
    "music": ""
  },
  {
    "number": 528,
    "title": "Велик си Ти",
    "alias": "",
    "ppt": "LINK/download",
    "text": "LINK/download",
    "notes": "LINK/download",
    "music": ""
  },
  {
    "number": 529,
    "title": "Божи ден, святи ден",
    "alias": "",
    "ppt": "LINK/download",
    "text": "LINK/download",
    "notes": "LINK/download",
    "music": ""
  },
  {
    "number": 530,
    "title": "Царството Божие",
    "alias": "",
    "ppt": "LINK/download",
    "text": "LINK/download",
    "notes": "LINK/download",
    "music": ""
  },
  {
    "number": 531,
    "title": "Слава, слава",
    "alias": "",
    "ppt": "LINK/download",
    "text": "LINK/download",
    "notes": "LINK/download",
    "music": ""
  },
  {
    "number": 532,
    "title": "Ти ела в сърцето мое",
    "alias": "",
    "ppt": "LINK/download",
    "text": "LINK/download",
    "notes": "LINK/download",
    "music": ""
  },
  {
    "number": 533,
    "title": "Близо до кръста",
    "alias": "",
    "ppt": "LINK/download",
    "text": "LINK/download",
    "notes": "LINK/download",
    "music": ""
  },
  {
    "number": 534,
    "title": "Утро настъпва",
    "alias": "",
    "ppt": "LINK/download",
    "text": "LINK/download",
    "notes": "LINK/download",
    "music": ""
  },
  {
    "number": 535,
    "title": "Спасен – аз обичам да казвам",
    "alias": "",
    "ppt": "LINK/download",
    "text": "LINK/download",
    "notes": "LINK/download",
    "music": ""
  },
  {
    "number": 536,
    "title": "Боже свят и велик",
    "alias": "",
    "ppt": "LINK/download",
    "text": "LINK/download",
    "notes": "LINK/download",
    "music": ""
  },
  {
    "number": 537,
    "title": "Запей хвала на Господа",
    "alias": "",
    "ppt": "LINK/download",
    "text": "LINK/download",
    "notes": "LINK/download",
    "music": ""
  },
  {
    "number": 538,
    "title": "Колко добро е за братя",
    "alias": "",
    "ppt": "LINK/download",
    "text": "LINK/download",
    "notes": "LINK/download",
    "music": ""
  },
  {
    "number": 539,
    "title": "Мили Татко небесни",
    "alias": "",
    "ppt": "LINK/download",
    "text": "LINK/download",
    "notes": "LINK/download",
    "music": ""
  },
  {
    "number": 540,
    "title": "Ден след ден",
    "alias": "",
    "ppt": "LINK/download",
    "text": "LINK/download",
    "notes": "LINK/download",
    "music": ""
  },
  {
    "number": 541,
    "title": "Покланяме се, Отче",
    "alias": "",
    "ppt": "LINK/download",
    "text": "LINK/download",
    "notes": "LINK/download",
    "music": ""
  },
  {
    "number": 542,
    "title": "При Твойте нозе",
    "alias": "",
    "ppt": "LINK/download",
    "text": "LINK/download",
    "notes": "LINK/download",
    "music": ""
  },
  {
    "number": 543,
    "title": "В този свят, Боже мой",
    "alias": "",
    "ppt": "LINK/download",
    "text": "LINK/download",
    "notes": "LINK/download",
    "music": ""
  },
  {
    "number": 544,
    "title": "Бог обича нежно",
    "alias": "",
    "ppt": "LINK/download",
    "text": "LINK/download",
    "notes": "LINK/download",
    "music": ""
  },
  {
    "number": 545,
    "title": "О, кога ще видя аз Исуса",
    "alias": "",
    "ppt": "LINK/download",
    "text": "LINK/download",
    "notes": "LINK/download",
    "music": ""
  },
  {
    "number": 546,
    "title": "Вижте хор от ангели",
    "alias": "",
    "ppt": "LINK/download",
    "text": "LINK/download",
    "notes": "LINK/download",
    "music": ""
  }
]
